{"items":{"serializeList":[{"name":"hay","nr":13703280.0},{"name":"wood","nr":22832235.0},{"name":"carrot","nr":2464118.0},{"name":"pumpkin","nr":4320571.0},{"name":"cactus","nr":45264.0},{"name":"weird_substance","nr":12526.0},{"name":"gold","nr":532.0},{"name":"water","nr":2757016.0},{"name":"fertilizer","nr":71105.0}]},"dockedFiles":[{"key":"C_Cactus","value":"C_Functions"},{"key":"C_carrotAndTree","value":"main"},{"key":"C_Functions","value":"C_Pumpkin"},{"key":"C_Grass","value":"C_carrotAndTree"},{"key":"C_Maze","value":"cosecharTodo"},{"key":"C_Pumpkin","value":"C_Grass"},{"key":"maze_move","value":"C_Maze"}],"minimizedFiles":["cosecharTodo","C_Cactus","C_carrotAndTree","C_Functions","C_Grass","C_Maze","C_Pumpkin","add_def_grass","main","f0","maze_move","mainDrons","f1"],"openFilePositions":[{"key":"cosecharTodo","value":{"x":-247.3226318359375,"y":1718.143310546875}},{"key":"C_Cactus","value":{"x":1304.579345703125,"y":1772.5}},{"key":"C_carrotAndTree","value":{"x":1304.579345703125,"y":1772.5}},{"key":"C_Functions","value":{"x":1304.579345703125,"y":1772.5}},{"key":"C_Grass","value":{"x":1304.579345703125,"y":1772.5}},{"key":"C_Maze","value":{"x":1304.579345703125,"y":1772.5}},{"key":"C_Pumpkin","value":{"x":1304.579345703125,"y":1772.5}},{"key":"add_def_grass","value":{"x":-786.77734375,"y":1384.719970703125}},{"key":"main","value":{"x":-1390.841796875,"y":1839.197998046875}},{"key":"f0","value":{"x":140.9498291015625,"y":1096.29541015625}},{"key":"maze_move","value":{"x":1304.579345703125,"y":1772.5}},{"key":"mainDrons","value":{"x":-822.196044921875,"y":1586.259521484375}},{"key":"f1","value":{"x":-258.970458984375,"y":1504.662353515625}},{"key":"dron1","value":{"x":-1236.7060546875,"y":1107.415771484375}}],"openFileScrollPositions":[{"key":"cosecharTodo","value":0.00079345703125},{"key":"C_Cactus","value":113.38844299316406},{"key":"C_carrotAndTree","value":549.9891967773438},{"key":"C_Functions","value":0.0},{"key":"C_Grass","value":-0.0008544921875},{"key":"C_Maze","value":-0.0023193359375},{"key":"C_Pumpkin","value":0.0},{"key":"add_def_grass","value":0.0},{"key":"main","value":-0.0006103515625},{"key":"f0","value":0.0},{"key":"maze_move","value":-49.999847412109378},{"key":"mainDrons","value":50.0},{"key":"f1","value":500.00079345703127},{"key":"dron1","value":-0.000701904296875}],"openFileSizes":[{"key":"cosecharTodo","value":{"x":0.0,"y":0.0}},{"key":"C_Cactus","value":{"x":0.0,"y":1587.149658203125}},{"key":"C_carrotAndTree","value":{"x":0.0,"y":1085.302978515625}},{"key":"C_Functions","value":{"x":0.0,"y":0.0}},{"key":"C_Grass","value":{"x":0.0,"y":479.7449951171875}},{"key":"C_Maze","value":{"x":0.0,"y":406.0846252441406}},{"key":"C_Pumpkin","value":{"x":0.0,"y":1182.2559814453125}},{"key":"add_def_grass","value":{"x":0.0,"y":872.820556640625}},{"key":"main","value":{"x":708.6179809570313,"y":1183.1407470703125}},{"key":"f0","value":{"x":0.0,"y":0.0}},{"key":"maze_move","value":{"x":0.0,"y":0.0}},{"key":"mainDrons","value":{"x":683.1795043945313,"y":461.1281433105469}},{"key":"f1","value":{"x":0.0,"y":0.0}},{"key":"dron1","value":{"x":798.1537475585938,"y":566.3588256835938}}],"openDocPages":[],"unlocks":["grass_9","soil","harvest","pass","do_a_flip","pet_the_piggy","grassland","hay","straw_hat","tap","traffic_cone","while","true","false","break","continue","loops","speed_5","can_harvest","if","else","elif","change_hat","gray_hat","purple_hat","green_hat","brown_hat","hats","expand_9","move","north","south","east","west","for","range","get_world_size","wood","bush","entities","clear","plant","and","or","not","operators","print","quick_print","unlocks","str","debug","carrots_9","carrot","till","can_trade","trade","items","carrot_seed","get_entity_type","get_ground_type","grounds","get_pos_x","get_pos_y","none","num_items","num_unlocked","senses","tree_hat","carrot_hat","variables","trees_9","tree","pumpkins_8","pumpkin","pumpkin_seed","dead_pumpkin","watering_9","water","use_item","get_water","functions","def","return","global","from","import","wizard_hat","pumpkin_hat","fertilizer_4","weird_substance","get_time","get_tick_count","timing","append","remove","pop","insert","len","list","lists","dicts","sets","add","dict","set","dictionaries","mazes_2","hedge","treasure","gold","measure","can_move","cactus_5","swap","cactus_seed","cactus_hat","gold_hat","megafarm","get_drone_id","num_drones","max_drones","wait_for","spawn_drone","has_finished"],"version":3}